odoo10_addon_agreement_account-10.0.1.0.0.99.dev21-py3.8-nspkg.pth
odoo/addons/agreement_account/README.rst
odoo/addons/agreement_account/__init__.py
odoo/addons/agreement_account/__manifest__.py
odoo/addons/agreement_account/demo/demo.xml
odoo/addons/agreement_account/i18n/agreement_account.pot
odoo/addons/agreement_account/i18n/am.po
odoo/addons/agreement_account/i18n/ar.po
odoo/addons/agreement_account/i18n/bg.po
odoo/addons/agreement_account/i18n/bs.po
odoo/addons/agreement_account/i18n/ca.po
odoo/addons/agreement_account/i18n/cs.po
odoo/addons/agreement_account/i18n/da.po
odoo/addons/agreement_account/i18n/de.po
odoo/addons/agreement_account/i18n/el_GR.po
odoo/addons/agreement_account/i18n/en_GB.po
odoo/addons/agreement_account/i18n/es.po
odoo/addons/agreement_account/i18n/es_AR.po
odoo/addons/agreement_account/i18n/es_CO.po
odoo/addons/agreement_account/i18n/es_CR.po
odoo/addons/agreement_account/i18n/es_DO.po
odoo/addons/agreement_account/i18n/es_EC.po
odoo/addons/agreement_account/i18n/es_ES.po
odoo/addons/agreement_account/i18n/es_MX.po
odoo/addons/agreement_account/i18n/es_PY.po
odoo/addons/agreement_account/i18n/es_VE.po
odoo/addons/agreement_account/i18n/et.po
odoo/addons/agreement_account/i18n/eu.po
odoo/addons/agreement_account/i18n/fa.po
odoo/addons/agreement_account/i18n/fi.po
odoo/addons/agreement_account/i18n/fr.po
odoo/addons/agreement_account/i18n/fr_CA.po
odoo/addons/agreement_account/i18n/fr_CH.po
odoo/addons/agreement_account/i18n/gl.po
odoo/addons/agreement_account/i18n/gl_ES.po
odoo/addons/agreement_account/i18n/he.po
odoo/addons/agreement_account/i18n/hi_IN.po
odoo/addons/agreement_account/i18n/hr.po
odoo/addons/agreement_account/i18n/hr_HR.po
odoo/addons/agreement_account/i18n/hu.po
odoo/addons/agreement_account/i18n/id.po
odoo/addons/agreement_account/i18n/it.po
odoo/addons/agreement_account/i18n/ja.po
odoo/addons/agreement_account/i18n/ko.po
odoo/addons/agreement_account/i18n/lt.po
odoo/addons/agreement_account/i18n/lt_LT.po
odoo10_addon_agreement_account-10.0.1.0.0.99.dev21.dist-info/METADATA
odoo10_addon_agreement_account-10.0.1.0.0.99.dev21.dist-info/WHEEL
odoo10_addon_agreement_account-10.0.1.0.0.99.dev21.dist-info/namespace_packages.txt
odoo10_addon_agreement_account-10.0.1.0.0.99.dev21.dist-info/top_level.txt
odoo10_addon_agreement_account-10.0.1.0.0.99.dev21.dist-info/RECORD
